eu_state_aids/__init__.py
eu_state_aids/__main__.py
eu_state_aids/bg.py
eu_state_aids/it.py
eu_state_aids/main.py
eu_state_aids/utils.py
eu_state_aids-0.2.3.dist-info/entry_points.txt
eu_state_aids-0.2.3.dist-info/LICENSE.txt
eu_state_aids-0.2.3.dist-info/WHEEL
eu_state_aids-0.2.3.dist-info/METADATA
eu_state_aids-0.2.3.dist-info/RECORD
