Metadata-Version: 2.1
Name: eu-state-aids
Version: 0.2.3
Summary: CLI to extract state aids data from public sources and produce CSV files
Home-page: https://github.com/openpolis/eu-state-aids/
License: MIT
Author: guglielmo
Author-email: guglielmo@openpolis.it
Maintainer: guglielmo
Maintainer-email: guglielmo@openpolis.it
Requires-Python: >=3.7.1,<4
Classifier: License :: OSI Approved :: MIT License
Classifier: Programming Language :: Python :: 3
Classifier: Programming Language :: Python :: 3.8
Classifier: Programming Language :: Python :: 3.9
Requires-Dist: importlib-metadata (>=4.5.0,<5.0.0)
Requires-Dist: openpyxl (>=3.0.7,<4.0.0)
Requires-Dist: pandas (>=1.2.5,<2.0.0)
Requires-Dist: pandas-read-xml (>=0.3.1,<0.4.0)
Requires-Dist: requests (>=2.25.1,<3.0.0)
Requires-Dist: requests-mock (>=1.9.3,<2.0.0)
Requires-Dist: typer (>=0.3.2,<0.4.0)
Requires-Dist: validators (>=0.18.2,<0.19.0)
Project-URL: Repository, https://github.com/openpolis/eu-state-aids/
